{
  "id": 1010,
  "name": "iron-leaves",
  "classification": "패러독스포켓몬",
  "height": 1.5,
  "weight": 125,
  "gender": "성별없음",
  "flavorTexts": [
    {
      "version": "스칼렛",
      "text": "어떤 지역에서만 재배되는 특별한 사과에 의해 진화했다. 두 마리가 하나인 포켓몬이다.<br />\n※북신의 고장 모험을 통해 만날 수 있습니다."
    },
    {
      "version": "바이올렛",
      "text": "머리를 내밀고 있는 외미르와 꼬리를 내밀고 있는 내미르가 사과 안에서 서로 도우며 지낸다.<br />\n※북신의 고장 모험을 통해 만날 수 있습니다."
    }
  ],
  "abilities": [
    {
      "name": "quark-drive",
      "description": "설명이 없습니다."
    }
  ]
}