{
  "id": 454,
  "name": "toxicroak",
  "classification": "독설포켓몬",
  "height": 1.3,
  "weight": 44.4,
  "gender": "수컷, 암컷",
  "flavorTexts": [
    {
      "version": "X",
      "text": "목 주변에 독주머니를 지녔다. 목을 울리면 모여진 독이 잘 섞여져서 강력해진다."
    },
    {
      "version": "Y",
      "text": "주먹의 가시는 긁히기만 해도 생명을 잃을 정도의 맹독을 분비하고 있다."
    },
    {
      "version": "오메가루비",
      "text": "목 주변에 독주머니를 지녔다. 목을 울리면 모여진 독이 잘 섞여져서 강력해진다."
    },
    {
      "version": "알파사파이어",
      "text": "주먹의 가시는 긁히기만 해도 생명을 잃을 정도의 맹독을 분비하고 있다."
    },
    {
      "version": "소드",
      "text": "튀어 오르듯 상대에게 다가간 뒤 독손톱으로 찌르듯이 공격한다! 스치기만 해도 상대는 KO다."
    },
    {
      "version": "실드",
      "text": "사냥감을 처리하면 개굴개굴하며 승리를 자축하는 소리를 높인다. 두빅굴과 가까운 종이다."
    }
  ],
  "abilities": [
    {
      "name": "위험예지",
      "description": "상대가 지닌 위험한\n기술을 감지한다."
    },
    {
      "name": "건조피부",
      "description": "더우면 HP가 줄어든다.\n물로 HP를 회복한다."
    },
    {
      "name": "독수",
      "description": "접촉하기만 해도 상대를\n독 상태로 만들 때가 있다."
    }
  ]
}