{
  "id": 551,
  "name": "sandile",
  "classification": "사막악어포켓몬",
  "height": 0.7,
  "weight": 15.2,
  "gender": "수컷, 암컷",
  "flavorTexts": [
    {
      "version": "X",
      "text": "모래 속에 파고들어 눈과 코를 밖에 내놓고 이동한다. 검은 막이 눈을 보호한다."
    },
    {
      "version": "Y",
      "text": "사막의 모래 속에서 생활한다. 태양 때문에 따뜻해진 모래가 체온 저하를 막아준다."
    },
    {
      "version": "오메가루비",
      "text": "모래 속에 파고들어 눈과 코를 밖에 내놓고 이동한다. 검은 막이 눈을 보호한다."
    },
    {
      "version": "알파사파이어",
      "text": "사막의 모래 속에서 생활한다. 태양 때문에 따뜻해진 모래가 체온 저하를 막아준다."
    },
    {
      "version": "썬",
      "text": "모래 속에 숨어서 헤엄치는 것처럼 이동한다. 적에게 들키지 않으면서 체온이 내려가지 않기 위한 지혜다."
    },
    {
      "version": "문",
      "text": "모래 속에 몸을 숨기고 위를 걸어가는 먹이의 다리를 덥석 문다. 가장 좋아하는 것은 톱치."
    },
    {
      "version": "울트라썬",
      "text": "일 년 내내 따듯한 알로라는 지내기 좋은 환경이다. 사막이 아닌 곳에서도 가끔 볼 수 있다."
    },
    {
      "version": "울트라문",
      "text": "아직 사냥은 서툴러서 주로 사막에서 객사한 것을 먹는다. 사막의 청소부라 불린다."
    },
    {
      "version": "소드",
      "text": "사막의 밤은 기온이 낮기 때문에 모래 깊숙이 파고들어 해가 뜰 때까지 잠을 자면서 생활한다."
    },
    {
      "version": "실드",
      "text": "작지만 하체의 힘은 세다. 모래를 헤치며 사막을 헤엄치듯 이동한다."
    }
  ],
  "abilities": [
    {
      "name": "위협",
      "description": "상대의 공격을\n떨어뜨린다."
    },
    {
      "name": "자기과신",
      "description": "상대를 쓰러뜨리면\n공격이 올라간다."
    },
    {
      "name": "분노의경혈",
      "description": "급소에 맞으면\n공격이 올라간다."
    }
  ]
}