{
  "id": 595,
  "name": "joltik",
  "classification": "들러붙기포켓몬",
  "height": 0.1,
  "weight": 0.6,
  "gender": "수컷, 암컷",
  "flavorTexts": [
    {
      "version": "X",
      "text": "스스로 전기를 만들 수 없어 다른 큰 포켓몬에 달라붙어 정전기를 흡수한다."
    },
    {
      "version": "Y",
      "text": "몸이 큰 포켓몬에게 매달려 정전기를 빨아들인 후 축전 주머니에 전기를 모은다."
    },
    {
      "version": "오메가루비",
      "text": "스스로 전기를 만들 수 없어 다른 큰 포켓몬에 달라붙어 정전기를 흡수한다."
    },
    {
      "version": "알파사파이어",
      "text": "몸이 큰 포켓몬에게 매달려 정전기를 빨아들인 후 축전 주머니에 전기를 모은다."
    },
    {
      "version": "소드",
      "text": "포켓몬의 몸에 들러붙어 정전기를 흡수한다. 스스로는 전기를 만들 수 없다."
    },
    {
      "version": "실드",
      "text": "다른 포켓몬에게 달라붙어 정전기를 빨아들인다. 멍파치의 엉덩이에 자주 달라붙어 있다."
    }
  ],
  "abilities": [
    {
      "name": "복안",
      "description": "기술의 명중률이\n올라간다."
    },
    {
      "name": "긴장감",
      "description": "상대를 긴장시켜 나무열매를\n먹지 못하게 한다."
    },
    {
      "name": "벌레의알림",
      "description": "위급할 때 벌레타입의\n위력이 올라간다."
    }
  ]
}