{
  "id": 618,
  "name": "stunfisk",
  "classification": "트랩포켓몬",
  "height": 0.7,
  "weight": 11,
  "gender": "수컷, 암컷",
  "flavorTexts": [
    {
      "version": "X",
      "text": "피부가 단단해서 씨름꾼에게 밟혀도 아무렇지 않다. 전기를 흘려보낼 때 웃는 얼굴이 된다."
    },
    {
      "version": "Y",
      "text": "바닷가 펄 속에 묻혀 먹이를 기다린다. 먹이가 몸에 닿으면 전기를 써서 마비시킨다."
    },
    {
      "version": "오메가루비",
      "text": "피부가 단단해서 씨름꾼에게 밟혀도 아무렇지 않다. 전기를 흘려보낼 때 웃는 얼굴이 된다."
    },
    {
      "version": "알파사파이어",
      "text": "바닷가 펄 속에 묻혀 먹이를 기다린다. 먹이가 몸에 닿으면 전기를 써서 마비시킨다."
    },
    {
      "version": "소드",
      "text": "갯벌이 보금자리다. 진흙 속에 사는 세균에 의해 전기를 만드는 기관이 발달했다."
    },
    {
      "version": "실드",
      "text": "몸의 노란 무늬에서 강한 전기를 발산할 때 무슨 이유인지 살짝 웃고 있다."
    }
  ],
  "abilities": [
    {
      "name": "정전기",
      "description": "접촉한 상대를\n마비시킬 때가 있다."
    },
    {
      "name": "유연",
      "description": "마비 상태가\n되지 않는다."
    },
    {
      "name": "모래숨기",
      "description": "모래바람으로\n회피율이 올라간다."
    }
  ]
}