{
  "id": 624,
  "name": "pawniard",
  "classification": "날붙이포켓몬",
  "height": 0.5,
  "weight": 10.2,
  "gender": "수컷, 암컷",
  "flavorTexts": [
    {
      "version": "X",
      "text": "전신이 칼날인 포켓몬이다. 싸움에서 칼의 이가 빠지면 강가의 돌로 칼을 간다."
    },
    {
      "version": "Y",
      "text": "자신이 상처 입어도 신경 쓰지 않고 집단으로 전신의 칼날을 박아서 상대를 공격한다."
    },
    {
      "version": "오메가루비",
      "text": "전신이 칼날인 포켓몬이다. 싸움에서 칼의 이가 빠지면 강가의 돌로 칼을 간다."
    },
    {
      "version": "알파사파이어",
      "text": "자신이 상처 입어도 신경 쓰지 않고 집단으로 전신의 칼날을 박아서 상대를 공격한다."
    },
    {
      "version": "울트라썬",
      "text": "먹이를 베어 가른 후에는 기와 돌로 칼날을 간다. 자망칼마다 좋아하는 돌이 있다."
    },
    {
      "version": "울트라문",
      "text": "절각참의 명령에 따라 적을 공격한다. 상대를 베어 가르면 양손의 칼날을 부딪친다."
    },
    {
      "version": "소드",
      "text": "예리한 칼날을 다루어 상대를 몰아넣는다. 강가에 있는 돌로 몸에 있는 칼날을 손질한다."
    },
    {
      "version": "실드",
      "text": "절각참을 보스로 둔 무리를 만든다. 무리를 이끄는 날을 꿈꾸며 날마다 단련을 계속한다."
    }
  ],
  "abilities": [
    {
      "name": "오기",
      "description": "능력이 떨어지면\n공격이 올라간다."
    },
    {
      "name": "정신력",
      "description": "풀죽지 않는다."
    },
    {
      "name": "프레셔",
      "description": "상대가 사용하는 기술의\nPP를 많이 줄인다."
    }
  ]
}