{
  "id": 769,
  "name": "sandygast",
  "classification": "모래산포켓몬",
  "height": 0.5,
  "weight": 70,
  "gender": "수컷, 암컷",
  "flavorTexts": [
    {
      "version": "썬",
      "text": "객사한 자의 원통함이 아이가 만든 모래언덕에 깃들어 탄생했다."
    },
    {
      "version": "문",
      "text": "입안에 손을 넣은 자를 조종한다. 모래언덕의 몸집을 크게 만들기 위해서다."
    },
    {
      "version": "울트라썬",
      "text": "머리의 삽을 마음에 들어한다. 되찾으러 온 아이와 싸우다가 열을 올리면서 치고 받고 싸운다."
    },
    {
      "version": "울트라문",
      "text": "모래장난으로 만든 모래산은 돌아갈 때 부수지 않으면 영혼이 깃들어서 모래꿍이 될지도 모른다."
    },
    {
      "version": "소드",
      "text": "모래산에 죽은 자의 원념이 깃들어 포켓몬이 되었다. 머리의 삽을 마음에 들어 한다."
    },
    {
      "version": "실드",
      "text": "주로 모래사장에 산다. 입안에 손을 넣은 상대를 조종하여 자신을 크게 만든다."
    }
  ],
  "abilities": [
    {
      "name": "꾸덕꾸덕굳기",
      "description": "물타입의 기술을 받으면\n방어가 크게 올라간다."
    },
    {
      "name": "모래숨기",
      "description": "모래바람으로\n회피율이 올라간다."
    }
  ]
}